{
  "audit_report": {
    "dag_valid": true,
    "cycle_detected": false,
    "cycles_found": [],
    "missing_nodes": [],
    "orphan_modules": [
      "sdlc_os.__init__",
      "healer.repair_strategies",
      "healer.patch_generator",
      "healer.planner"
    ],
    "drift_consistency": 1.0,
    "architecture_health": "stable",
    "nodes": 18,
    "edges": 25,
    "sorted_order_length": 12,
    "core_modules_present": true
  },
  "risk_score": 0.022,
  "healer_status": "enabled",
  "repair_plan": [
    {
      "target_node": "unknown",
      "issue_type": "unexpected_new_nodes",
      "proposed_fix": "Classify unknown (type: unknown) and establish module boundary",
      "risk_level": 0.3,
      "strategy_category": "structural_repair",
      "estimated_impact": "Node type validated, may require __init__.py or classification"
    }
  ],
  "git_push_package": {
    "commit_message": "release: sdlc-os phase2 - healer engine\n\nAudit: DAG=valid, risk=0.022\nHealer: enabled\nPlans: 1",
    "changed_files": [
      "core.py",
      "sdlc_types.py",
      "phase2.py",
      "__init__.py",
      "engine.py",
      "__init__.py",
      "drift_detector.py",
      "repo_scanner.py",
      "__init__.py",
      "semantic_diff.py"
    ],
    "architecture_diff_summary": "18 nodes, 25 edges, 4 orphans",
    "safety_status": "safe",
    "rollback_hint": "git reset --hard HEAD~1 to revert"
  },
  "system_health": "stable"
}